<?xml version="1.0" encoding="UTF-8"?>
<objects serializationModel="Studio.02.02.00">
	<object class="AudioFile" id="{80832389-59e0-4838-bab2-7207a38fe145}">
		<property name="assetPath">
			<value>Voices/RpgTheGame_Vo_Attack-013.wav</value>
		</property>
		<property name="frequencyInKHz">
			<value>48</value>
		</property>
		<property name="channelCount">
			<value>2</value>
		</property>
		<property name="length">
			<value>1.4072916666666666</value>
		</property>
		<relationship name="masterAssetFolder">
			<destination>{34db6cde-1739-454e-b735-958293805eb1}</destination>
		</relationship>
	</object>
</objects>
