<?xml version="1.0" encoding="UTF-8"?>
<objects serializationModel="Studio.02.02.00">
	<object class="AudioFile" id="{fc20842f-678d-415d-bc03-996a61228ba8}">
		<property name="assetPath">
			<value>Narra/RpgTheGame_Narra_DefeatChapter5.wav</value>
		</property>
		<property name="isStreaming">
			<value>true</value>
		</property>
		<property name="frequencyInKHz">
			<value>48</value>
		</property>
		<property name="channelCount">
			<value>2</value>
		</property>
		<property name="length">
			<value>11.194333333333333</value>
		</property>
		<relationship name="masterAssetFolder">
			<destination>{34db6cde-1739-454e-b735-958293805eb1}</destination>
		</relationship>
	</object>
</objects>
